gpu4pyscf/__config__.py
gpu4pyscf/__init__.py
gpu4pyscf/_patch_pyscf.py
gpu4pyscf/cc/__init__.py
gpu4pyscf/cc/ccsd_incore.py
gpu4pyscf/df/__init__.py
gpu4pyscf/df/cderi.py
gpu4pyscf/df/df.py
gpu4pyscf/df/df_jk.py
gpu4pyscf/df/int3c2e.py
gpu4pyscf/df/int3c2e_bdiv.py
gpu4pyscf/df/j_engine_3c2e.py
gpu4pyscf/df/grad/__init__.py
gpu4pyscf/df/grad/jk.py
gpu4pyscf/df/grad/rhf.py
gpu4pyscf/df/grad/rks.py
gpu4pyscf/df/grad/tdrhf.py
gpu4pyscf/df/grad/tdrks.py
gpu4pyscf/df/grad/tdrks_ris.py
gpu4pyscf/df/grad/tduhf.py
gpu4pyscf/df/grad/tduks.py
gpu4pyscf/df/grad/uhf.py
gpu4pyscf/df/grad/uks.py
gpu4pyscf/df/hessian/__init__.py
gpu4pyscf/df/hessian/jk.py
gpu4pyscf/df/hessian/rhf.py
gpu4pyscf/df/hessian/rks.py
gpu4pyscf/df/hessian/uhf.py
gpu4pyscf/df/hessian/uks.py
gpu4pyscf/df/nac/__init__.py
gpu4pyscf/df/nac/tdrhf.py
gpu4pyscf/df/nac/tdrks.py
gpu4pyscf/df/nac/tdrks_ris.py
gpu4pyscf/dft/__init__.py
gpu4pyscf/dft/gen_grid.py
gpu4pyscf/dft/gks.py
gpu4pyscf/dft/libxc.py
gpu4pyscf/dft/libxc_structs.py
gpu4pyscf/dft/mcfun_gpu.py
gpu4pyscf/dft/numint.py
gpu4pyscf/dft/numint2c.py
gpu4pyscf/dft/radi.py
gpu4pyscf/dft/rks.py
gpu4pyscf/dft/rks_lowmem.py
gpu4pyscf/dft/rkspu.py
gpu4pyscf/dft/roks.py
gpu4pyscf/dft/uks.py
gpu4pyscf/dft/ukspu.py
gpu4pyscf/dft/xc_alias.py
gpu4pyscf/dft/xc_deriv.py
gpu4pyscf/drivers/__init__.py
gpu4pyscf/drivers/basis_vDZP_NWCHEM.dat
gpu4pyscf/drivers/dft_3c_driver.py
gpu4pyscf/drivers/dft_driver.py
gpu4pyscf/drivers/ecp_vDZP_NWCHEM.dat
gpu4pyscf/drivers/opt_3c_driver.py
gpu4pyscf/drivers/opt_driver.py
gpu4pyscf/fci/__init__.py
gpu4pyscf/fci/direct_spin1.py
gpu4pyscf/geomopt/__init__.py
gpu4pyscf/geomopt/ase_solver.py
gpu4pyscf/grad/__init__.py
gpu4pyscf/grad/rhf.py
gpu4pyscf/grad/rks.py
gpu4pyscf/grad/rkspu.py
gpu4pyscf/grad/tdrhf.py
gpu4pyscf/grad/tdrks.py
gpu4pyscf/grad/tdrks_ris.py
gpu4pyscf/grad/tduhf.py
gpu4pyscf/grad/tduks.py
gpu4pyscf/grad/tduks_sf.py
gpu4pyscf/grad/uhf.py
gpu4pyscf_cuda13x-1.5.2.dist-info/METADATA
gpu4pyscf_cuda13x-1.5.2.dist-info/WHEEL
gpu4pyscf_cuda13x-1.5.2.dist-info/top_level.txt
gpu4pyscf_cuda13x-1.5.2.dist-info/RECORD
gpu4pyscf_cuda13x-1.5.2.dist-info/licenses/LICENSE
gpu4pyscf_cuda13x-1.5.2.dist-info/sboms/auditwheel.cdx.json
