Metadata-Version: 2.4
Name: gpu4pyscf-cuda13x
Version: 1.5.2
Summary: GPU extensions for PySCF
Author: PySCF developers
License: Apache-2.0
License-File: LICENSE
Requires-Dist: pyscf>=2.8.0
Requires-Dist: pyscf-dispersion
Requires-Dist: cupy-cuda13x!=13.4.0,>=13.0
Requires-Dist: geometric
Requires-Dist: gpu4pyscf-libxc-cuda13x==0.5
Dynamic: author
Dynamic: license
Dynamic: license-file
Dynamic: requires-dist
Dynamic: summary
